ansys/api/dbu/VERSION
ansys/api/dbu/__init__.py
ansys/api/dbu/py.typed
ansys/api/dbu/v0/admin.proto
ansys/api/dbu/v0/admin_pb2.py
ansys/api/dbu/v0/admin_pb2.pyi
ansys/api/dbu/v0/admin_pb2_grpc.py
ansys/api/dbu/v0/admin_pb2_grpc.pyi
ansys/api/dbu/v0/dbuapi.proto
ansys/api/dbu/v0/dbuapi_pb2.py
ansys/api/dbu/v0/dbuapi_pb2.pyi
ansys/api/dbu/v0/dbuapi_pb2_grpc.py
ansys/api/dbu/v0/dbuapi_pb2_grpc.pyi
ansys/api/dbu/v0/dbuapplication.proto
ansys/api/dbu/v0/dbuapplication_pb2.py
ansys/api/dbu/v0/dbuapplication_pb2.pyi
ansys/api/dbu/v0/dbuapplication_pb2_grpc.py
ansys/api/dbu/v0/dbuapplication_pb2_grpc.pyi
ansys/api/dbu/v0/dbumodels.proto
ansys/api/dbu/v0/dbumodels_pb2.py
ansys/api/dbu/v0/dbumodels_pb2.pyi
ansys/api/dbu/v0/dbumodels_pb2_grpc.py
ansys/api/dbu/v0/dbumodels_pb2_grpc.pyi
ansys/api/dbu/v0/dbuwebmodels.proto
ansys/api/dbu/v0/dbuwebmodels_pb2.py
ansys/api/dbu/v0/dbuwebmodels_pb2.pyi
ansys/api/dbu/v0/dbuwebmodels_pb2_grpc.py
ansys/api/dbu/v0/dbuwebmodels_pb2_grpc.pyi
ansys/api/dbu/v0/designs.proto
ansys/api/dbu/v0/designs_pb2.py
ansys/api/dbu/v0/designs_pb2.pyi
ansys/api/dbu/v0/designs_pb2_grpc.py
ansys/api/dbu/v0/designs_pb2_grpc.pyi
ansys/api/dbu/v0/drivingdimensions.proto
ansys/api/dbu/v0/drivingdimensions_pb2.py
ansys/api/dbu/v0/drivingdimensions_pb2.pyi
ansys/api/dbu/v0/drivingdimensions_pb2_grpc.py
ansys/api/dbu/v0/drivingdimensions_pb2_grpc.pyi
ansys/api/dbu/v0/sessionmanager.proto
ansys/api/dbu/v0/sessionmanager_pb2.py
ansys/api/dbu/v0/sessionmanager_pb2.pyi
ansys/api/dbu/v0/sessionmanager_pb2_grpc.py
ansys/api/dbu/v0/sessionmanager_pb2_grpc.pyi
ansys/api/dbu/v0/streaming.proto
ansys/api/dbu/v0/streaming_pb2.py
ansys/api/dbu/v0/streaming_pb2.pyi
ansys/api/dbu/v0/streaming_pb2_grpc.py
ansys/api/dbu/v0/streaming_pb2_grpc.pyi
ansys/api/dbu/v0/windows.proto
ansys/api/dbu/v0/windows_pb2.py
ansys/api/dbu/v0/windows_pb2.pyi
ansys/api/dbu/v0/windows_pb2_grpc.py
ansys/api/dbu/v0/windows_pb2_grpc.pyi
ansys_api_dbu-0.3.28.dist-info/licenses/LICENSE
ansys_api_dbu-0.3.28.dist-info/METADATA
ansys_api_dbu-0.3.28.dist-info/WHEEL
ansys_api_dbu-0.3.28.dist-info/entry_points.txt
ansys_api_dbu-0.3.28.dist-info/top_level.txt
ansys_api_dbu-0.3.28.dist-info/RECORD
