Metadata-Version: 2.4
Name: ansys-api-dbu
Version: 0.3.28
Summary: Autogenerated Python gRPC interface package for ansys-api-dbu, built on 07:31:53 on 20 October 2025
Home-page: https://github.com/ansys/ansys-api-dbu
Author: ANSYS, Inc.
Author-email: pyansys.core@ansys.com
Maintainer: ANSYS, Inc.
Maintainer-email: pyansys.core@ansys.com
License: MIT
Project-URL: Documentation, https://github.com/ansys/ansys-api-dbu/#readme
Project-URL: Source, https://github.com/ansys/ansys-api-dbu/
Project-URL: Tracker, https://github.com/ansys/ansys-api-dbu/issues/
Requires-Python: >=3.10
License-File: LICENSE
Requires-Dist: grpcio~=1.44
Requires-Dist: protobuf<7,>=3.19
Dynamic: author
Dynamic: author-email
Dynamic: description
Dynamic: description-content-type
Dynamic: home-page
Dynamic: license
Dynamic: license-file
Dynamic: maintainer
Dynamic: maintainer-email
Dynamic: project-url
Dynamic: requires-dist
Dynamic: requires-python
Dynamic: summary
